fplpandas/__init__.py
pandas_fpl-0.3.4.dist-info/LICENSE
pandas_fpl-0.3.4.dist-info/METADATA
pandas_fpl-0.3.4.dist-info/WHEEL
pandas_fpl-0.3.4.dist-info/top_level.txt
pandas_fpl-0.3.4.dist-info/RECORD
