Metadata-Version: 2.1
Name: pandas-fpl
Version: 0.3.4
Summary: Pandas wrapper for Fantasy Premier League API based on the FPL package: https://github.com/amosbastian/fpl
Home-page: https://github.com/177arc/pandas-fpl
Author: Marc Maier
Author-email: py@177arc.net
License: MIT
Platform: UNKNOWN
Classifier: License :: OSI Approved :: MIT License
Classifier: Programming Language :: Python :: 3
Classifier: Programming Language :: Python :: 3.6
Classifier: Programming Language :: Python :: 3.7
Requires-Dist: pandas
Requires-Dist: fpl
Requires-Dist: backoff
